aws_sm_import/__init__.py
aws_sm_import/cli.py
aws_sm_import-0.2.0.dist-info/entry_points.txt
aws_sm_import-0.2.0.dist-info/WHEEL
aws_sm_import-0.2.0.dist-info/METADATA
aws_sm_import-0.2.0.dist-info/RECORD
