Metadata-Version: 2.1
Name: aws-sm-import
Version: 0.2.0
Summary: Import AWS SecretsManager secrets from specific file
Author: Epsy Engineering
Author-email: engineering@epsyhealth.com
Requires-Python: >=3.6.2,<4.0.0
Classifier: Programming Language :: Python :: 3
Classifier: Programming Language :: Python :: 3.10
Classifier: Programming Language :: Python :: 3.7
Classifier: Programming Language :: Python :: 3.8
Classifier: Programming Language :: Python :: 3.9
Requires-Dist: PyYAML (>=6.0,<7.0)
Requires-Dist: boto3 (>=1.21.22,<2.0.0)
Requires-Dist: click (>=8.0.4,<9.0.0)
Requires-Dist: python-dotenv (>=0.19.2,<0.20.0)
